fileshard/__init__.py
fileshard/file.py
fileshard/shard.py
fileshard-1.0.8.dist-info/METADATA
fileshard-1.0.8.dist-info/WHEEL
fileshard-1.0.8.dist-info/top_level.txt
fileshard-1.0.8.dist-info/RECORD
