Metadata-Version: 2.1
Name: fileshard
Version: 1.0.8
Summary: File splitting tool
Home-page: https://github.com/NoelKaczmarek/fileshard
Author: Noel Kaczmarek
Author-email: noel.Kaczmarek@gmail.com
License: UNKNOWN
Download-URL: https://github.com/NoelKaczmarek/fileshard/archive/1.0.0.tar.gz
Keywords: file split splits chunks
Platform: UNKNOWN
